Metadata-Version: 1.2
Name: xorgauth
Version: 0.1.0
Summary: Polytechnique.org authentication provider
Home-page: https://github.com/Polytechnique-org/xorgauth
Author: Polytechnique.org dev team
Author-email: devel+xorgauth@staff.polytechnique.org
License: AGPLv3
Download-URL: http://pypi.python.org/pypi/xorgauth/
Keywords: sso,authentication,authgroupex,openid connect
Platform: UNKNOWN
Classifier: Development Status :: 3 - Alpha
Classifier: Environment :: Web Environment
Classifier: Framework :: Django
Classifier: License :: OSI Approved :: GNU Affero General Public License v3
Classifier: Natural Language :: French
Classifier: Natural Language :: English
Classifier: Operating System :: OS Independent
Classifier: Programming Language :: Python :: 3 :: Only
Classifier: Topic :: Internet :: WWW/HTTP :: Session
Classifier: Topic :: System :: Systems Administration :: Authentication/Directory
Requires-Python: >=3.4.2
